LICENSE.txt
MANIFEST.in
README.md
requirements.txt
setup.py
questeval/__init__.py
questeval/questeval_metric.py
questeval/utils.py
questeval.egg-info/PKG-INFO
questeval.egg-info/SOURCES.txt
questeval.egg-info/dependency_links.txt
questeval.egg-info/requires.txt
questeval.egg-info/top_level.txt
questeval/logs/__init__.py
tests/__init__.py
tests/resources/__init__.py
tests/resources/constants.py
tests/units/__init__.py
tests/units/test_questeval_metric.py
tests/utils/__init__.py
tests/utils/helpers.py