Metadata-Version: 2.1
Name: questeval
Version: 0.2.4
Summary: State-of-the-art metric for Natural Language Generation
Home-page: https://github.com/ThomasScialom/QuestEval
Author: Thomas Scialom, Paul-Alexis Dray
Author-email: t.scialom@gmail.com
License: MIT
Keywords: NLP NLG Metric Evaluation Summarization Simplification Image Captioning Data2text Question Answering Generation Multilingual deep learning Transformer Pytorch
Platform: UNKNOWN
Classifier: Intended Audience :: Developers
Classifier: Intended Audience :: Education
Classifier: Intended Audience :: Science/Research
Classifier: License :: OSI Approved :: MIT License
Classifier: Operating System :: OS Independent
Classifier: Topic :: Scientific/Engineering :: Artificial Intelligence
Classifier: Programming Language :: Python
Classifier: Programming Language :: Python :: 3
Classifier: Programming Language :: Python :: 3.7
Classifier: Programming Language :: Python :: 3.8
Classifier: Programming Language :: Python :: 3.9
Requires-Python: >=3.6.0
